taxoniq_accession_db/__init__.py
taxoniq_accession_db-2021.2.9.dist-info/METADATA
taxoniq_accession_db-2021.2.9.dist-info/WHEEL
taxoniq_accession_db-2021.2.9.dist-info/top_level.txt
taxoniq_accession_db-2021.2.9.dist-info/RECORD
