Metadata-Version: 2.1
Name: taxoniq-accession-db
Version: 2021.2.9
Summary: Taxoniq accession index for NCBI BLAST databases
Home-page: https://github.com/chanzuckerberg/taxoniq
Author: Andrey Kislyuk
Author-email: akislyuk@chanzuckerberg.com
License: MIT License
Platform: UNKNOWN
